Workbook
Name Slicer_MonthName: #N/A
Name Slicer_Region: #N/A
Name Slicer_Salesperson: #N/A

Sheet Sales By Region
A3: Row Labels | B3: Sum of Total Sales | C3: Sum of Profit
A4: East | B4: 233908.95 | C4: 58788.42

Sheet Monthly Sales Trend
A3: Row Labels | B3: Sum of Total Sales
A4: May | B4: 233908.95

Sheet Top 5 Product By profit
A3: Row Labels | B3: Sum of Total Sales | C3: Sum of Profit
A4: Dell Inspiron | B4: 233908.95 | C4: 58788.42

Sheet Sales Person Performance
A3: Row Labels | B3: Count of Quantity | C3: Sum of Profit
A4: Rohan Das | B4: 1 | C4: 58788.42

Sheet Category Wise Profit & Discount
A3: Row Labels | B3: Sum of Total Sales | C3: Sum of Profit | D3: Average of Discount
A4: Electronics | B4: 233908.95 | C4: 58788.42 | D4: 0.07

Sheet Raw_Data
A1: Order ID | B1: Date | C1: Customer Name | D1: Product Category | E1: Sub-Category | F1: Product Name | G1: Salesperson | H1: Region | I1: Quantity | J1: Unit Price | K1: Discount | L1: Total Sales | M1: Cost | N1: Profit | O1: MonthNum | P1: MonthName | Q1: Year
A2: O-1001 | B2: 14-Apr-2025 | C2: Aman Tiwari | D2: Appliances | E2: Washing Machine | F2: Bosch 7kg | G2: Riya Gupta | H2: South | I2: 5 | J2: 52061 | K2: 0.11 | L2: 231671.45 | M2: 187803.16 | N2: 43868.29 | O2: =MONTH(TblSales[[#This Row],[Date]]) -> 4 | P2: =TEXT(TblSales[[#This Row],[Date]],"mmm") -> Apr | Q2: =YEAR(TblSales[[#This Row],[Date]]) -> 2025
A3: O-1002 | B3: 09-Jun-2025 | C3: Pooja Jain | D3: Furniture | E3: Table | F3: Study Table | G3: Aman Singh | H3: North | I3: 5 | J3: 5012 | K3: 0.11 | L3: 22303.4 | M3: 15744.31 | N3: 6559.09 | O3: =MONTH(TblSales[[#This Row],[Date]]) -> 6 | P3: =TEXT(TblSales[[#This Row],[Date]],"mmm") -> Jun | Q3: =YEAR(TblSales[[#This Row],[Date]]) -> 2025
A4: O-1003 | B4: 12-Apr-2025 | C4: Kiran Singh | D4: Appliances | E4: Washing Machine | F4: Bosch 7kg | G4: Simran Kaur | H4: West | I4: 4 | J4: 35352 | K4: 0.09 | L4: 128681.28 | M4: 110730.22 | N4: 17951.06 | O4: =MONTH(TblSales[[#This Row],[Date]]) -> 4 | P4: =TEXT(TblSales[[#This Row],[Date]],"mmm") -> Apr | Q4: =YEAR(TblSales[[#This Row],[Date]]) -> 2025
A5: O-1004 | B5: 04-Feb-2025 | C5: Ravi Patel | D5: Appliances | E5: Microwave | F5: IFB 20L | G5: Rohan Das | H5: North | I5: 4 | J5: 40081 | K5: 0.02 | L5: 157117.52 | M5: 125971.64 | N5: 31145.88 | O5: =MONTH(TblSales[[#This Row],[Date]]) -> 2 | P5: =TEXT(TblSales[[#This Row],[Date]],"mmm") -> Feb | Q5: =YEAR(TblSales[[#This Row],[Date]]) -> 2025
A6: O-1005 | B6: 22-Sep-2025 | C6: Aman Tiwari | D6: Furniture | E6: Bookshelf | F6: Metal Rack | G6: Neha Joshi | H6: West | I6: 1 | J6: 24914 | K6: 0.06 | L6: 23419.16 | M6: 20772.84 | N6: 2646.32 | O6: =MONTH(TblSales[[#This Row],[Date]]) -> 9 | P6: =TEXT(TblSales[[#This Row],[Date]],"mmm") -> Sep | Q6: =YEAR(TblSales[[#This Row],[Date]]) -> 2025
A7: O-1006 | B7: 30-Jun-2025 | C7: Aman Tiwari | D7: Appliances | E7: Refrigerator | F7: LG Double Door | G7: Neha Joshi | H7: South | I7: 5 | J7: 48252 | K7: 0.1 | L7: 217134 | M7: 176588.42 | N7: 40545.58 | O7: =MONTH(TblSales[[#This Row],[Date]]) -> 6 | P7: =TEXT(TblSales[[#This Row],[Date]],"mmm") -> Jun | Q7: =YEAR(TblSales[[#This Row],[Date]]) -> 2025
A8: O-1007 | B8: 29-Jan-2025 | C8: Deepak Chauhan | D8: Clothing | E8: Jeans | F8: Slim Fit Jeans | G8: Simran Kaur | H8: East | I8: 4 | J8: 48263 | K8: 0.09 | L8: 175677.32 | M8: 143606.46 | N8: 32070.86 | O8: =MONTH(TblSales[[#This Row],[Date]]) -> 1 | P8: =TEXT(TblSales[[#This Row],[Date]],"mmm") -> Jan | Q8: =YEAR(TblSales[[#This Row],[Date]]) -> 2025
A9: O-1008 | B9: 14-Jan-2025 | C9: Nikhil Joshi | D9: Electronics | E9: Mobile | F9: Samsung Galaxy A14 | G9: Riya Gupta | H9: East | I9: 4 | J9: 34950 | K9: 0.1 | L9: 125820 | M9: 97561.96 | N9: 28258.04 | O9: =MONTH(TblSales[[#This Row],[Date]]) -> 1 | P9: =TEXT(TblSales[[#This Row],[Date]],"mmm") -> Jan | Q9: =YEAR(TblSales[[#This Row],[Date]]) -> 2025
A10: O-1009 | B10: 04-May-2025 | C10: Deepak Chauhan | D10: Electronics | E10: Tablet | F10: iPad Air | G10: Kavita Rao | H10: East | I10: 4 | J10: 51240 | K10: 0.13 | L10: 178315.2 | M10: 125248.13 | N10: 53067.07 | O10: =MONTH(TblSales[[#This Row],[Date]]) -> 5 | P10: =TEXT(TblSales[[#This Row],[Date]],"mmm") -> May | Q10: =YEAR(TblSales[[#This Row],[Date]]) -> 2025
A11: O-1010 | B11: 11-Aug-2025 | C11: Deepak Chauhan | D11: Furniture | E11: Chair | F11: Mesh Chair | G11: Kavita Rao | H11: North | I11: 2 | J11: 19368 | K11: 0.04 | L11: 37186.56 | M11: 27432.52 | N11: 9754.04 | O11: =MONTH(TblSales[[#This Row],[Date]]) -> 8 | P11: =TEXT(TblSales[[#This Row],[Date]],"mmm") -> Aug | Q11: =YEAR(TblSales[[#This Row],[Date]]) -> 2025
A12: O-1011 | B12: 17-Apr-2025 | C12: Deepak Chauhan | D12: Appliances | E12: Mixer | F12: Prestige Iris | G12: Rohan Das | H12: South | I12: 5 | J12: 3180 | K12: 0.13 | L12: 13833 | M12: 9960.5 | N12: 3872.5 | O12: =MONTH(TblSales[[#This Row],[Date]]) -> 4 | P12: =TEXT(TblSales[[#This Row],[Date]],"mmm") -> Apr | Q12: =YEAR(TblSales[[#This Row],[Date]]) -> 2025
A13: O-1012 | B13: 25-Mar-2025 | C13: Ravi Patel | D13: Clothing | E13: Jeans | F13: Regular Fit Jeans | G13: Simran Kaur | H13: North | I13: 3 | J13: 22021 | K13: 0.09 | L13: 60117.33 | M13: 43125.99 | N13: 16991.34 | O13: =MONTH(TblSales[[#This Row],[Date]]) -> 3 | P13: =TEXT(TblSales[[#This Row],[Date]],"mmm") -> Mar | Q13: =YEAR(TblSales[[#This Row],[Date]]) -> 2025
... A501: O-1500 | B501: 21-Apr-2025 | C501: Raj Sharma | D501: Clothing | E501: Jeans | F501: Stretch Jeans | G501: Rohan Das | H501: West | I501: 1 | J501: 49343 | K501: 0.14 | L501: 42434.98 | M501: 32484.59 | N501: 9950.39 | O501: =MONTH(TblSales[[#This Row],[Date]]) -> 4 | P501: =TEXT(TblSales[[#This Row],[Date]],"mmm") -> Apr | Q501: =YEAR(TblSales[[#This Row],[Date]]) -> 2025
I505: =SUM(TblSales[Total Sales]) -> 42879432
L506: Products | M506: Total Sales
L507: S2 | M507: 20
L508: S3 | M508: 30
L509: S4 | M509: 40
L510: S5 | M510: 50
L511: S6 | M511: 60
O512: =SUM(Table2[Total Sales]) -> 200

Sheet Product_Master
A1: Product Name | B1: Supplier | C1: Rating | D1: Warranty
A2: Samsung Galaxy A14 | B2: Levi's | C2: 4.5 | D2: 6 Months
A3: Redmi Note 12 | B3: FeatherLite | C3: 4 | D3: 2 Years
A4: iPhone 13 | B4: Whirlpool | C4: 3.9 | D4: 1 Year
A5: Realme Narzo 60 | B5: LG Electronics | C5: 4.7 | D5: 6 Months
A6: HP Pavilion 15 | B6: FeatherLite | C6: 4.7 | D6: 6 Months
A7: Dell Inspiron | B7: FeatherLite | C7: 3.8 | D7: 2 Years
A8: Lenovo IdeaPad | B8: HP India | C8: 3.8 | D8: 1 Year
A9: Asus Vivobook | B9: HP India | C9: 4.4 | D9: 2 Years
A10: iPad Air | B10: Samsung India | C10: 4.1 | D10: 1 Year
A11: Lenovo Tab M10 | B11: Boat | C11: 4.4 | D11: 2 Years
A12: Samsung Tab S6 | B12: Samsung India | C12: 4 | D12: 1 Year
A13: Realme Pad | B13: Whirlpool | C13: 4.3 | D13: 2 Years
... A65: Prestige Iris | B65: FeatherLite | C65: 4.3 | D65: 6 Months

Sheet Targets
A1: Region | B1: North | C1: South | D1: East | E1: West
A2: Monthly Target | B2: 800000 | C2: 750000 | D2: 600000 | E2: 650000
A3: Jan | B3: =SUMIFS(TblSales[Total Sales],TblSales[Region], "North",TblSales[MonthNum],1) -> 1332553.6 | C3: =SUMIFS(TblSales[Total Sales],TblSales[Region], "South", TblSales[MonthNum],1) -> 1111103 | D3: =SUMIFS(TblSales[Total Sales],TblSales[Region], "East",TblSales[MonthNum],1) -> 1199853.7 | E3: =SUMIFS(TblSales[Total Sales],TblSales[Region],"West",TblSales[MonthNum],1) -> 908109.65

Sheet Formula_Guide
A1: Category | B1: Function | C1: Example Formula | D1: Purpose / Description
A2: Basic Math | B2: SUM | C2: =SUM(Raw_Data!L2:L501) -> 42879432 | D2: Calculates total sales amount
A3: Basic Math | B3: AVERAGE | C3: =AVERAGE(Raw_Data!N2:N501) -> 17400.487 | D3: Finds average profit
A4: Conditional | B4: IF | C4: =IF(Raw_Data!N2>0,"Profit","Loss") -> Profit | D4: Checks if profit is positive
A5: Conditional | B5: SUMIF | C5: =SUMIF(Raw_Data!H:H,"North",Raw_Data!L:L) -> 10672917 | D5: Total sales for North region
A6: Conditional | B6: COUNTIF | C6: =COUNTIF(Raw_Data!H:H,"South") -> 126 | D6: Counts orders from South region
A7: Conditional | B7: SUMIFS | C7: =SUMIFS(Raw_Data!L:L,Raw_Data!H:H,"West",Raw_Data!D:D,"Electronics") -> 2527296.6 | D7: Total Electronics sales in West
A8: Lookup | B8: VLOOKUP | C8: =VLOOKUP(Raw_Data!F2,Product_Master!A:D,2,FALSE) -> LG Electronics | D8: Fetch supplier from Product Master
A9: Lookup | B9: HLOOKUP | C9: =HLOOKUP(Raw_Data!H2,Targets!A1:E2,2,FALSE) -> 750000 | D9: Fetch target for given region
A10: Lookup | B10: INDEX+MATCH | C10: =INDEX(Raw_Data!H:H,MATCH(MAX(Raw_Data!N:N),Raw_Data!N:N,0)) -> West | D10: Find region with max profit
A11: Text | B11: CONCATENATE | C11: =CONCATENATE(Raw_Data!C2," - ",Raw_Data!F2) -> Aman Tiwari - Bosch 7kg | D11: Combine customer and product name
A12: Text | B12: PROPER | C12: =PROPER(Raw_Data!C2) -> Aman Tiwari | D12: Converts customer name to proper case
A13: Date | B13: MONTH | C13: =MONTH(Raw_Data!B2) -> 4 | D13: Extracts month number from date
A14: Date | B14: YEAR | C14: =YEAR(Raw_Data!B2) -> 2025 | D14: Extracts year from date
A15: Formatting | B15: Conditional Formatting | C15: Highlight cells > average | D15: Use Home → Conditional Formatting
A16: Dashboard | B16: Pivot Table | C16: Insert → PivotTable | D16: Summarize data by Region, Product, etc.

Sheet Analysis
A1: Total Sales | B1: Total Profit | C1: Total Orders | D1: Average Order Value | E1: Average Profit Margin | F1: Order with Loss
A2: =SUM(TblSales[Total Sales]) -> 42879432 | B2: =SUM(TblSales[Profit]) -> 8700243.4 | C2: =COUNTA(TblSales[Order ID]) -> 500 | D2: =SUM(TblSales[Total Sales]) -> 42879432 | E2: =AVERAGE(TblSales[Profit]/TblSales[Total Sales]) -> 0.18935562 | F2: =COUNTIF(TblSales[Profit], "0") -> 0
C8: =SUM(Analysis!M507:M511) -> 0
C13: =SUM(Table2[Total Sales]) -> 200

Sheet Dashboard
